{
  "title": "Qatar - Tourist/Visit Visa",
  "image": "https://cg-website-s3.s3.ap-south-1.amazonaws.com/0000/7/2024/12/17/icons8-qatar-72.png",
  "visa_fee": "7,000 BDT",
  "processing_time": "1–2 working days (Chologhuri file processing time)",
  "validity": "30 Days Stay - Single Entry",
  "details": [
    {
      "title": "Eligibility",
      "items": [
        "Bangladeshi citizens must apply for a Qatar tourist visa prior to travel.",
        "Must hold a valid UK, USA, Schengen, or Ireland visa.",
        "Passport must be valid and available in both current and any previous versions.",
        "Visa approval is at the discretion of the Qatar Embassy and may require a personal interview."
      ]
    },
    {
      "title": "Required Documents",
      "items": [
        "Scanned copy of valid passport (color).",
        "Recent passport-size photo (digital scan).",
        "Scan copy of valid visa for UK, USA, Schengen, or Ireland (mandatory)."
      ]
    }
  ],
  "note": "Chologhuri does not process urgent visas or non-tourist categories. File submission preparation takes 1–2 working days. The embassy may request additional documents. Visa issuance is not guaranteed and entirely at the discretion of the Qatar Embassy."
}